PyGeneratePassword/__init__.py
PyGeneratePassword-0.1.dist-info/LICENSE.txt
PyGeneratePassword-0.1.dist-info/METADATA
PyGeneratePassword-0.1.dist-info/WHEEL
PyGeneratePassword-0.1.dist-info/top_level.txt
PyGeneratePassword-0.1.dist-info/RECORD
