Metadata-Version: 2.1
Name: PyGeneratePassword
Version: 0.1
Summary: Generate Random password
Home-page: https://pypi.org/project/PyGeneratePassword/
Author: Md. Ismiel Hossen Abir
License: MIT
License-File: LICENSE.txt
